{
  "version": 1,
  "capturedOn": "2026-07-16",
  "approvedBaseline": {
    "sourceCommit": "95b884ebdf12553ebe213bef01c45412abb54a3f",
    "portalQa": {
      "attestation": "docs/qa-attestations/integration-feature-freeze-phase1-20260716.json",
      "artifact": "output/playwright/integration-freeze-phase1-20260716/portal-qa-summary.json",
      "artifactSha256": "d0f99f5d5c4e6b22b15c6dcd31d44ca7e63fb940b21965d2064a25e3a8169573",
      "totalChecks": 1598,
      "failedChecks": 0
    }
  },
  "protectedSurface": {
    "roles": [
      "branchadmin",
      "headofdepartment",
      "registrar",
      "student",
      "superadmin",
      "teacher"
    ],
    "clientRoutes": [
      "/",
      "/404",
      "/about",
      "/app",
      "/app/admin/audit-logs",
      "/app/admin/branches",
      "/app/admin/certificates",
      "/app/admin/courses",
      "/app/admin/courses/:courseId",
      "/app/admin/courses/curriculum",
      "/app/admin/courses/levels",
      "/app/admin/courses/programs",
      "/app/admin/courses/resources",
      "/app/admin/courses/teachers",
      "/app/admin/dashboard",
      "/app/admin/departments",
      "/app/admin/forms",
      "/app/admin/forms/:publicationId",
      "/app/admin/forms/:publicationId/responses/:submissionId",
      "/app/admin/forms/manage",
      "/app/admin/forms/manage/:formId/builder",
      "/app/admin/forms/manage/:formId/publications",
      "/app/admin/forms/manage/:formId/publications/:publicationId/assignments",
      "/app/admin/forms/manage/:formId/publish",
      "/app/admin/forms/manage/new",
      "/app/admin/forms/migration",
      "/app/admin/forms/offline",
      "/app/admin/forms/review",
      "/app/admin/forms/review/:submissionId",
      "/app/admin/integrations",
      "/app/admin/messages",
      "/app/admin/messages/new",
      "/app/admin/moodle-source",
      "/app/admin/moodle-source/:courseId",
      "/app/admin/permissions",
      "/app/admin/platform-blueprint",
      "/app/admin/profile",
      "/app/admin/programs",
      "/app/admin/reports",
      "/app/admin/reports/admissions",
      "/app/admin/reports/attendance",
      "/app/admin/reports/certificates",
      "/app/admin/reports/classes",
      "/app/admin/reports/finance",
      "/app/admin/reports/saved-views",
      "/app/admin/roles",
      "/app/admin/schedule",
      "/app/admin/schedule/activity",
      "/app/admin/schedule/calendar",
      "/app/admin/schedule/conflicts",
      "/app/admin/schedule/rooms",
      "/app/admin/schedule/sessions",
      "/app/admin/settings",
      "/app/admin/settings/profile",
      "/app/admin/system-health",
      "/app/admin/users",
      "/app/admin/users/:userId",
      "/app/admin/users/:userId/access",
      "/app/admin/users/:userId/activity",
      "/app/admin/users/:userId/assignment",
      "/app/admin/users/:userId/related",
      "/app/admin/users/new",
      "/app/branch/attendance",
      "/app/branch/classes",
      "/app/branch/classes/:classGroupId",
      "/app/branch/classes/new",
      "/app/branch/dashboard",
      "/app/branch/forms",
      "/app/branch/forms/:publicationId",
      "/app/branch/forms/:publicationId/responses/:submissionId",
      "/app/branch/forms/manage",
      "/app/branch/forms/manage/:formId/builder",
      "/app/branch/forms/manage/:formId/publications",
      "/app/branch/forms/manage/:formId/publications/:publicationId/assignments",
      "/app/branch/forms/manage/:formId/publish",
      "/app/branch/forms/manage/new",
      "/app/branch/forms/offline",
      "/app/branch/forms/review",
      "/app/branch/forms/review/:submissionId",
      "/app/branch/messages",
      "/app/branch/messages/new",
      "/app/branch/payments",
      "/app/branch/payments/:invoiceId",
      "/app/branch/profile",
      "/app/branch/reports",
      "/app/branch/rooms",
      "/app/branch/rooms/new",
      "/app/branch/schedule",
      "/app/branch/schedule/new",
      "/app/branch/schedule/sessions/:sessionId",
      "/app/branch/settings",
      "/app/branch/settings/profile",
      "/app/branch/students",
      "/app/branch/teachers",
      "/app/hod/assessments",
      "/app/hod/assessments/new",
      "/app/hod/assessments/review",
      "/app/hod/assessments/review/:submissionId",
      "/app/hod/certificates",
      "/app/hod/certificates/:certificateId",
      "/app/hod/classes",
      "/app/hod/classes/runs/new",
      "/app/hod/courses",
      "/app/hod/courses/:courseId",
      "/app/hod/curriculum",
      "/app/hod/curriculum/new",
      "/app/hod/dashboard",
      "/app/hod/departments",
      "/app/hod/forms",
      "/app/hod/forms/:publicationId",
      "/app/hod/forms/:publicationId/responses/:submissionId",
      "/app/hod/forms/manage",
      "/app/hod/forms/manage/:formId/builder",
      "/app/hod/forms/manage/:formId/publications",
      "/app/hod/forms/manage/:formId/publications/:publicationId/assignments",
      "/app/hod/forms/manage/:formId/publish",
      "/app/hod/forms/manage/new",
      "/app/hod/forms/offline",
      "/app/hod/forms/review",
      "/app/hod/forms/review/:submissionId",
      "/app/hod/levels",
      "/app/hod/messages",
      "/app/hod/messages/new",
      "/app/hod/moodle-source",
      "/app/hod/moodle-source/:courseId",
      "/app/hod/profile",
      "/app/hod/programs",
      "/app/hod/reports",
      "/app/hod/schedule",
      "/app/hod/schedule/sessions",
      "/app/hod/settings",
      "/app/hod/settings/profile",
      "/app/hod/teachers",
      "/app/registrar/applications",
      "/app/registrar/applications/:applicationId",
      "/app/registrar/applications/:applicationId/placement",
      "/app/registrar/applications/new",
      "/app/registrar/classes",
      "/app/registrar/dashboard",
      "/app/registrar/enrollments",
      "/app/registrar/enrollments/:workflowId",
      "/app/registrar/enrollments/records",
      "/app/registrar/enrollments/records/:enrollmentId",
      "/app/registrar/forms",
      "/app/registrar/forms/:publicationId",
      "/app/registrar/forms/:publicationId/responses/:submissionId",
      "/app/registrar/forms/manage",
      "/app/registrar/forms/manage/:formId/builder",
      "/app/registrar/forms/manage/:formId/publications",
      "/app/registrar/forms/manage/:formId/publications/:publicationId/assignments",
      "/app/registrar/forms/manage/:formId/publish",
      "/app/registrar/forms/manage/new",
      "/app/registrar/forms/offline",
      "/app/registrar/forms/review",
      "/app/registrar/forms/review/:submissionId",
      "/app/registrar/leads",
      "/app/registrar/leads/:leadId",
      "/app/registrar/leads/new",
      "/app/registrar/messages",
      "/app/registrar/messages/new",
      "/app/registrar/payments",
      "/app/registrar/payments/:invoiceId",
      "/app/registrar/placement-tests",
      "/app/registrar/placement-tests/:bookingId",
      "/app/registrar/placement-tests/new",
      "/app/registrar/profile",
      "/app/registrar/reports",
      "/app/registrar/reports/admissions",
      "/app/registrar/reports/payments",
      "/app/registrar/schedule",
      "/app/registrar/schedule/new",
      "/app/registrar/settings",
      "/app/registrar/settings/profile",
      "/app/registrar/students",
      "/app/registrar/students/:studentId",
      "/app/registrar/students/new",
      "/app/student/assignments",
      "/app/student/assignments/:assignmentId",
      "/app/student/attendance",
      "/app/student/calendar",
      "/app/student/certificates",
      "/app/student/courses",
      "/app/student/courses/:courseId",
      "/app/student/courses/:courseId/learn/:lessonId",
      "/app/student/courses/:courseId/live",
      "/app/student/dashboard",
      "/app/student/forms",
      "/app/student/forms/:publicationId",
      "/app/student/forms/:publicationId/responses/:submissionId",
      "/app/student/forms/offline",
      "/app/student/grades",
      "/app/student/messages",
      "/app/student/messages/new",
      "/app/student/moodle-source",
      "/app/student/moodle-source/:courseId",
      "/app/student/profile",
      "/app/student/quizzes",
      "/app/student/quizzes/:quizId",
      "/app/student/quran-progress",
      "/app/student/reports",
      "/app/student/settings",
      "/app/student/support",
      "/app/student/support/new",
      "/app/teacher/assignments",
      "/app/teacher/assignments/:assignmentId",
      "/app/teacher/assignments/new",
      "/app/teacher/calendar",
      "/app/teacher/calendar/new",
      "/app/teacher/classes",
      "/app/teacher/classes/:classId",
      "/app/teacher/classes/:classId/attendance",
      "/app/teacher/classes/:classId/materials",
      "/app/teacher/classes/:classId/sessions",
      "/app/teacher/classes/:classId/students",
      "/app/teacher/dashboard",
      "/app/teacher/forms",
      "/app/teacher/forms/:publicationId",
      "/app/teacher/forms/:publicationId/responses/:submissionId",
      "/app/teacher/forms/offline",
      "/app/teacher/grading",
      "/app/teacher/grading/:submissionId",
      "/app/teacher/messages",
      "/app/teacher/messages/new",
      "/app/teacher/moodle-source",
      "/app/teacher/moodle-source/:courseId",
      "/app/teacher/profile",
      "/app/teacher/question-bank",
      "/app/teacher/question-bank/new",
      "/app/teacher/quizzes",
      "/app/teacher/quizzes/:quizId",
      "/app/teacher/quizzes/new",
      "/app/teacher/quizzes/review",
      "/app/teacher/quizzes/review/:attemptId",
      "/app/teacher/quran-review",
      "/app/teacher/quran-review/:recitationId",
      "/app/teacher/reports",
      "/app/teacher/reports/attendance",
      "/app/teacher/reports/grades",
      "/app/teacher/settings",
      "/apply",
      "/auth/accept-invitation",
      "/auth/admin-login",
      "/auth/administration-login",
      "/auth/forgot-password",
      "/auth/login",
      "/auth/logout",
      "/auth/reset-password",
      "/auth/select-role",
      "/auth/student-login",
      "/book-free-trial",
      "/book-placement-test",
      "/classes",
      "/contact",
      "/courses",
      "/courses/:slug",
      "/courses/arabic",
      "/courses/english",
      "/courses/enterprise",
      "/courses/islamic-studies",
      "/courses/kids",
      "/courses/quran",
      "/courses/teacher-training",
      "/courses/turkish",
      "/dashboard",
      "/faq",
      "/forms/:slug",
      "/login",
      "/messages",
      "/notifications",
      "/payments",
      "/privacy",
      "/profile",
      "/registrar",
      "/registrar/payments",
      "/registrar/pending",
      "/registrar/register",
      "/reports",
      "/schedule",
      "/settings",
      "/student",
      "/student/attendance",
      "/student/courses",
      "/student/grades",
      "/student/schedule",
      "/students",
      "/teacher",
      "/teacher/attendance",
      "/teacher/classes",
      "/teacher/schedule",
      "/teacher/scores",
      "/terms",
      "/users",
      "/verify-certificate",
      "expression:`${route.prefix}/requests/:requestId`",
      "expression:`${route.prefix}/requests/from-submission/:submissionId`",
      "expression:`${route.prefix}/requests`"
    ],
    "workflowActions": [
      "application.convert",
      "application.create",
      "assignment.create",
      "assignment.grade",
      "assignment.status.update",
      "assignment.submit",
      "assignment.update",
      "attendance.exception.review",
      "attendance.exception.submit",
      "attendance.save",
      "branch.update",
      "calendar.create",
      "certificate.approve",
      "certificate.issue",
      "certificate.reject",
      "class.create",
      "class.session.cancel",
      "class.session.reschedule",
      "class.status.update",
      "class.update",
      "course-run.create",
      "course.status.update",
      "curriculum.module.create",
      "enrollment.activate",
      "enrollment.status.update",
      "enrollment.transfer",
      "integration.local_check",
      "integration.status.update",
      "lead.convert",
      "lead.create",
      "lesson.complete",
      "lesson.start",
      "material.publish.update",
      "message.read",
      "message.send",
      "notification.read",
      "payment.record",
      "permission.update",
      "placement.create",
      "placement.result.record",
      "portal.settings.save",
      "profile.update",
      "question.create",
      "quiz.create",
      "quiz.questions.set",
      "quiz.review",
      "quiz.status.update",
      "quiz.submit",
      "quiz.update",
      "quran.progress.update",
      "recitation.review",
      "recitation.submit",
      "record.save",
      "report.preset.save",
      "room.create",
      "room.status.update",
      "settings.save",
      "staff.user.create",
      "student.create",
      "student.document.add",
      "student.status.update",
      "system.health_check",
      "teacher.assign",
      "user.create",
      "user.update"
    ],
    "serverApiRoutes": [
      "GET /api/auth/session",
      "GET /api/certificates/verify",
      "GET /api/forms/assigned",
      "GET /api/forms/assigned/:publicationId",
      "GET /api/forms/assigned/:publicationId/draft",
      "GET /api/forms/assigned/:publicationId/submissions/:submissionId",
      "GET /api/forms/definitions",
      "GET /api/forms/definitions/:formId",
      "GET /api/forms/management-options",
      "GET /api/forms/migration/jotform/forms",
      "GET /api/forms/migration/jotform/runs",
      "GET /api/forms/migration/jotform/status",
      "GET /api/forms/public/:slug",
      "GET /api/forms/submissions",
      "GET /api/forms/submissions/:submissionId",
      "GET /api/forms/submissions/export",
      "GET /api/integrations/moodle/projections/classes/:classGroupId/activities/:activityProjectionId/outcomes",
      "GET /api/integrations/moodle/projections/classes/:classGroupId/assessment-status",
      "GET /api/integrations/moodle/projections/classes/:classGroupId/assignments/:assignmentProjectionId/outcomes",
      "GET /api/integrations/moodle/projections/classes/:classGroupId/enrollment-groups",
      "GET /api/integrations/moodle/projections/classes/:classGroupId/grade-items/:gradeItemProjectionId/outcomes",
      "GET /api/integrations/moodle/projections/classes/:classGroupId/quizzes/:quizProjectionId/attempts",
      "GET /api/integrations/moodle/projections/courses",
      "GET /api/integrations/moodle/projections/courses/:courseId/content",
      "GET /api/integrations/moodle/status",
      "GET /api/integrations/resend/status",
      "GET /api/integrations/supabase/status",
      "GET /api/internal/email-deliveries/process",
      "GET /api/platform/records",
      "GET /api/platform/state",
      "GET /api/requests",
      "GET /api/requests/:requestId",
      "GET /api/requests/from-submission/:submissionId",
      "POST /api/admin/user-invitations",
      "POST /api/auth/invitations/accept",
      "POST /api/auth/login",
      "POST /api/auth/logout",
      "POST /api/auth/password-change",
      "POST /api/auth/password-reset/confirm",
      "POST /api/auth/password-reset/request",
      "POST /api/forms/assigned/:publicationId/draft",
      "POST /api/forms/assigned/:publicationId/submit",
      "POST /api/forms/assignments/:assignmentId/revoke",
      "POST /api/forms/definitions",
      "POST /api/forms/definitions/:formId/draft",
      "POST /api/forms/definitions/:formId/versions/:versionId",
      "POST /api/forms/definitions/:formId/versions/:versionId/publish",
      "POST /api/forms/migration/jotform/import",
      "POST /api/forms/migration/jotform/inspect",
      "POST /api/forms/migration/jotform/preview",
      "POST /api/forms/migration/jotform/records/:recordId/reconcile",
      "POST /api/forms/offline/bundle",
      "POST /api/forms/offline/devices",
      "POST /api/forms/offline/devices/:deviceId/revoke",
      "POST /api/forms/offline/sync",
      "POST /api/forms/public/:slug/draft",
      "POST /api/forms/public/:slug/draft/load",
      "POST /api/forms/public/:slug/submit",
      "POST /api/forms/publications/:publicationId/assignments",
      "POST /api/forms/publications/:publicationId/retire",
      "POST /api/forms/submissions/:submissionId/promote",
      "POST /api/forms/submissions/:submissionId/review",
      "POST /api/forms/submissions/:submissionId/withdraw",
      "POST /api/integrations/resend/webhook",
      "POST /api/internal/email-deliveries/process",
      "POST /api/platform/records",
      "POST /api/platform/state/actions",
      "POST /api/platform/state/reset",
      "POST /api/requests/:requestId/assign",
      "POST /api/requests/:requestId/cancel",
      "POST /api/requests/:requestId/comment",
      "POST /api/requests/:requestId/reprioritize",
      "POST /api/requests/:requestId/resolve",
      "POST /api/requests/:requestId/start",
      "POST /api/requests/from-submission/:submissionId"
    ],
    "moodleReadFunctions": [
      "core_completion_get_activities_completion_status",
      "core_completion_get_course_completion_status",
      "core_course_get_categories",
      "core_course_get_contents",
      "core_course_get_course_module",
      "core_course_get_courses_by_field",
      "core_enrol_get_enrolled_users",
      "core_enrol_get_users_courses",
      "core_group_get_course_groupings",
      "core_group_get_course_groups",
      "core_group_get_course_user_groups",
      "core_user_get_users_by_field",
      "core_webservice_get_site_info",
      "gradereport_user_get_grade_items",
      "mod_assign_get_assignments",
      "mod_assign_get_grades",
      "mod_assign_get_submissions",
      "mod_book_get_books_by_courses",
      "mod_h5pactivity_get_attempts",
      "mod_h5pactivity_get_h5pactivities_by_courses",
      "mod_h5pactivity_get_results",
      "mod_lesson_get_lessons_by_courses",
      "mod_lesson_get_user_grade",
      "mod_page_get_pages_by_courses",
      "mod_quiz_get_attempt_review",
      "mod_quiz_get_quizzes_by_courses",
      "mod_quiz_get_user_attempts",
      "mod_resource_get_resources_by_courses",
      "mod_scorm_get_scorm_sco_tracks",
      "mod_scorm_get_scorms_by_courses",
      "mod_url_get_urls_by_courses"
    ],
    "moodleSandboxWriteFunctions": [
      "core_group_add_group_members",
      "core_group_create_groups",
      "core_group_delete_group_members",
      "core_group_delete_groups",
      "core_user_create_users",
      "core_user_delete_users",
      "core_user_get_users",
      "core_user_update_users",
      "core_webservice_get_site_info",
      "enrol_manual_enrol_users",
      "enrol_manual_unenrol_users"
    ]
  },
  "authorityInventory": {
    "identityRolesScopes": "Nile Learn",
    "admissionsStudentDocuments": "Nile Learn",
    "branchesRoomsScheduling": "Nile Learn",
    "attendanceExceptions": "Nile Learn",
    "internalMessagesNotifications": "Nile Learn",
    "paymentsCertificatesAudit": "Nile Learn",
    "moodleCourseContentActivities": "Moodle",
    "moodleSubmissionsAttemptsGrades": "Moodle; assignment results and quiz attempt summaries are approved as separate server-scoped read-only observations, while broader grade/feedback families remain pending",
    "legacyEms": "Finite migration evidence only"
  },
  "frozenOutOfScope": [
    "new product features",
    "production Moodle writes",
    "recurring legacy EMS synchronization or writeback",
    "payment gateway",
    "external email, SMS, or WhatsApp delivery",
    "meeting provider",
    "production file or media storage",
    "linked or shared Supabase schema promotion without a phase gate"
  ]
}
